ocad/__init__.py
ocad/ocad.py
ocad/ocad_grid_id_to_epsg.py
ocad/test/__init__.py
ocad-0.0.2.dist-info/DESCRIPTION.rst
ocad-0.0.2.dist-info/METADATA
ocad-0.0.2.dist-info/RECORD
ocad-0.0.2.dist-info/WHEEL
ocad-0.0.2.dist-info/metadata.json
ocad-0.0.2.dist-info/top_level.txt
