Metadata-Version: 2.0
Name: ocad
Version: 0.0.2
Summary: Module for handling ocad-files
Home-page: UNKNOWN
Author: Marius Huerzeler
Author-email: huerzeler.marius@gmail.com
License: MIT
Platform: UNKNOWN
Classifier: Development Status :: 4 - Beta
Classifier: License :: OSI Approved :: MIT License
Classifier: Programming Language :: Python :: 3
Classifier: Programming Language :: Python :: 3.2
Classifier: Programming Language :: Python :: 3.3
Classifier: Programming Language :: Python :: 3.4
Requires-Python: >=3
